einsum/__init__.py
einsum/lib.py
einsum-0.3.0.dist-info/LICENSE
einsum-0.3.0.dist-info/WHEEL
einsum-0.3.0.dist-info/METADATA
einsum-0.3.0.dist-info/RECORD
