Metadata-Version: 2.1
Name: einsum
Version: 0.3.0
Summary: Experimental implementation of torch/onnx einsum
Home-page: https://github.com/sorenlassen/einsum-experiment
License: MIT
Author: Soren Lassen
Author-email: sorenlassen@gmail.com
Requires-Python: >=3.8,<4.0
Classifier: License :: OSI Approved :: MIT License
Classifier: Programming Language :: Python :: 3
Classifier: Programming Language :: Python :: 3.8
Classifier: Programming Language :: Python :: 3.9
Classifier: Programming Language :: Python :: 3.10
